<?xml version="1.0" encoding="UTF-8"?>
<TextFlow xmlns="http://ns.adobe.com/textLayout/2008">
	<p>I wish I was a little bit <span id="madlib_blank_01">adjective ending in -er</span>.</p>
	<p>I wish I was a <span id="madlib_blank_02">noun</span>.</p>
	<p>I wish I had a <span id="madlib_blank_03">noun</span> who <span id="madlib_blank_04">past participle</span> good.</p>
	<p>I would <span id="madlib_blank_05">noun</span> <span id="madlib_blank_06">pronoun</span>.</p>
	<p>I wish I had a <span id="madlib_blank_06"></span> in a <span id="madlib_blank_07">noun</span> with a <span id="madlib_blank_08">noun</span></p>
	<p>and a six four <span id="madlib_blank_">noun</span>.</p>
</TextFlow>